araxai/__init__.py
araxai/ara.py
araxai-0.3.0.dist-info/LICENSE
araxai-0.3.0.dist-info/METADATA
araxai-0.3.0.dist-info/WHEEL
araxai-0.3.0.dist-info/top_level.txt
araxai-0.3.0.dist-info/RECORD
