Metadata-Version: 2.1
Name: araxai
Version: 0.3.0
Summary: ARAxai is an expainable AI tool based on association rule analysis (therefore ARA).It can be used as XAI method to describe maininfluencers in data as well as to explain model by simplification using association rule analysis. Key influencers of the target variable are extracted.
Home-page: https://github.com/petrmasa/araxai
Author: (C) Copyright 2021 - 2024 Petr Masa
Author-email: code@cleverminer.org
Classifier: Programming Language :: Python :: 3
Classifier: Programming Language :: Python :: 3.10
Classifier: Programming Language :: Python :: 3.11
Classifier: Programming Language :: Python :: 3.12
Classifier: Programming Language :: Python :: 3.13
Classifier: Development Status :: 5 - Production/Stable
Classifier: License :: OSI Approved :: GNU General Public License v3 (GPLv3)
Classifier: Operating System :: OS Independent
Requires-Python: >=3.8
License-File: LICENSE
Requires-Dist: cleverminer
Requires-Dist: matplotlib
